h5view/__init__.py
h5view/__main__.py
h5view/app.py
h5view/app.ui
h5view/gui.py
h5view/utils.py
h5view/ui/__init__.py
h5view/ui/app.py
h5view-0.1.0a1.dist-info/METADATA
h5view-0.1.0a1.dist-info/WHEEL
h5view-0.1.0a1.dist-info/entry_points.txt
h5view-0.1.0a1.dist-info/licenses/LICENCE
h5view-0.1.0a1.dist-info/RECORD
