Metadata-Version: 2.3
Name: h5view
Version: 0.1.0a1
Summary: A small app for viewing h5 files in a simple and clean way
Project-URL: Homepage, https://github.com/refeyn/h5view
Project-URL: Issues, https://github.com/refeyn/h5view/issues
Project-URL: Source, https://github.com/refeyn/h5view
Author-email: Matthew Joyce <matthew.joyce@refeyn.com>
License: MIT License
License-File: LICENCE
Keywords: h5py,hdf5
Classifier: Development Status :: 3 - Alpha
Classifier: Environment :: X11 Applications :: Qt
Classifier: Intended Audience :: Developers
Classifier: Intended Audience :: Science/Research
Classifier: License :: OSI Approved :: MIT License
Classifier: Programming Language :: Python :: 3
Classifier: Topic :: Scientific/Engineering :: Visualization
Classifier: Topic :: Utilities
Requires-Dist: h5py
Requires-Dist: hdf5plugin
Requires-Dist: numpy
Requires-Dist: pyside6
Provides-Extra: build
Requires-Dist: nuitka; extra == 'build'
Requires-Dist: ordered-set; extra == 'build'
Requires-Dist: zstandard; extra == 'build'
Provides-Extra: dev
Requires-Dist: black; extra == 'dev'
Requires-Dist: build; extra == 'dev'
Requires-Dist: isort; extra == 'dev'
Requires-Dist: mypy; extra == 'dev'
Requires-Dist: pre-commit; extra == 'dev'
Requires-Dist: pylint; extra == 'dev'
Requires-Dist: types-setuptools; extra == 'dev'
